Metadata-Version: 1.0
Name: Ordinati
Version: 0.1.1
Summary: Offline bookmark management command line tool
Home-page: https://github.com/Ordinati/Ordinati
Author: 
Author-email: UNKNOWN
License: AGPLv3
Platform: UNKNOWN
